odoo8_addon_donation_mass-8.0.0.1.0-py2.7-nspkg.pth
odoo8_addon_donation_mass-8.0.0.1.0.dist-info/top_level.txt
odoo8_addon_donation_mass-8.0.0.1.0.dist-info/WHEEL
odoo8_addon_donation_mass-8.0.0.1.0.dist-info/RECORD
odoo8_addon_donation_mass-8.0.0.1.0.dist-info/metadata.json
odoo8_addon_donation_mass-8.0.0.1.0.dist-info/DESCRIPTION.rst
odoo8_addon_donation_mass-8.0.0.1.0.dist-info/METADATA
odoo8_addon_donation_mass-8.0.0.1.0.dist-info/namespace_packages.txt
odoo_addons/donation_mass/product.py
odoo_addons/donation_mass/donation_mass_data.xml
odoo_addons/donation_mass/__openerp__.py
odoo_addons/donation_mass/donation_view.xml
odoo_addons/donation_mass/__init__.py
odoo_addons/donation_mass/mass_view.xml
odoo_addons/donation_mass/donation_mass_demo.xml
odoo_addons/donation_mass/mass.py
odoo_addons/donation_mass/README.rst
odoo_addons/donation_mass/donation.py
odoo_addons/donation_mass/security/ir.model.access.csv
odoo_addons/donation_mass/i18n/donation_mass.pot
odoo_addons/donation_mass/i18n/fr.po
odoo_addons/donation_mass/test/donation_mass.yml
odoo_addons/donation_mass/static/description/icon.png
